<?xml version="1.0" encoding="utf-8"?>
<weights>
   <backness>
      <weight>0.520601</weight>
      <weight>2.518953</weight>
      <weight>0.313720</weight>
      <weight>-2.061871</weight>
      <weight>-2.021658</weight>
      <weight>0.164910</weight>
      <weight>0.840190</weight>
      <weight>-0.843075</weight>
      <weight>-1.316887</weight>
      <weight>-1.197805</weight>
      <weight>-0.149283</weight>
      <weight>2.109799</weight>
      <weight>2.508779</weight>
      <weight>0.774828</weight>
      <weight>-0.486423</weight>
      <weight>-0.638619</weight>
      <weight>-0.345807</weight>
      <weight>1.129551</weight>
      <weight>0.662037</weight>
      <weight>-0.572525</weight>
      <weight>0.227519</weight>
      <weight>0.337683</weight>
      <weight>0.184552</weight>
      <weight>-0.367680</weight>
      <weight>0.479591</weight>
   </backness>
   <height>
      <weight>0.994364</weight>
      <weight>0.618541</weight>
      <weight>0.931752</weight>
      <weight>0.906731</weight>
      <weight>0.058528</weight>
      <weight>-1.678007</weight>
      <weight>-2.317860</weight>
      <weight>-2.721294</weight>
      <weight>-1.431465</weight>
      <weight>-0.126810</weight>
      <weight>1.367374</weight>
      <weight>1.149381</weight>
      <weight>1.439490</weight>
      <weight>1.026525</weight>
      <weight>0.468375</weight>
      <weight>-0.575368</weight>
      <weight>-0.582064</weight>
      <weight>0.010785</weight>
      <weight>0.987428</weight>
      <weight>0.171622</weight>
      <weight>0.220674</weight>
      <weight>0.076273</weight>
      <weight>-0.180898</weight>
      <weight>-0.220471</weight>
      <weight>0.702350</weight>
   </height>
</weights>